{
  "Jiri Prochazka|Khalil Rountree Jr.: Starts at|2025": [
    {
      "label": "Back Control",
      "type": "control",
      "actor": "Jiri Prochazka",
      "timestamp": "0:42"
    },
    {
      "label": "Back Control",
      "type": "control",
      "actor": "Jiri Prochazka",
      "timestamp": "2:29"
    },
    {
      "label": "Back Control",
      "type": "control",
      "actor": "Jiri Prochazka",
      "timestamp": "3:12"
    },
    {
      "label": "Stand Up",
      "type": "escape",
      "actor": "Khalil Rountree Jr.: Starts at",
      "timestamp": "4:20"
    },
    {
      "label": "Half Guard",
      "type": "guard",
      "actor": "Jiri Prochazka",
      "timestamp": "6:56"
    },
    {
      "label": "Back Control",
      "type": "control",
      "actor": "Jiri Prochazka",
      "timestamp": "8:07"
    },
    {
      "label": "Half Guard",
      "type": "guard",
      "actor": "Jiri Prochazka",
      "timestamp": "8:42"
    },
    {
      "label": "Single Leg Takedown",
      "type": "takedown",
      "actor": "Jiri Prochazka",
      "timestamp": "9:17"
    },
    {
      "label": "Half Guard",
      "type": "guard",
      "actor": "Jiri Prochazka",
      "timestamp": "9:17"
    },
    {
      "label": "Uchi Mata",
      "type": "takedown",
      "actor": "Jiri Prochazka",
      "timestamp": "9:56"
    },
    {
      "label": "Stand Up",
      "type": "escape",
      "actor": "Jiri Prochazka",
      "timestamp": "11:20"
    },
    {
      "label": "Back Control",
      "type": "control",
      "actor": "Jiri Prochazka",
      "timestamp": "12:11"
    },
    {
      "label": "Half Guard",
      "type": "guard",
      "actor": "Jiri Prochazka",
      "timestamp": "12:22"
    },
    {
      "label": "Back Control",
      "type": "control",
      "actor": "Jiri Prochazka",
      "timestamp": "16:33"
    },
    {
      "label": "Back Control",
      "type": "control",
      "actor": "Jiri Prochazka",
      "timestamp": "17:16"
    },
    {
      "label": "Float Pass",
      "type": "pass",
      "actor": "Jiri Prochazka",
      "timestamp": "17:29",
      "successful": false
    },
    {
      "label": "Back Control",
      "type": "control",
      "actor": "Jiri Prochazka",
      "timestamp": "18:41"
    },
    {
      "label": "Back Control",
      "type": "control",
      "actor": "Jiri Prochazka",
      "timestamp": "19:16"
    },
    {
      "label": "Back Control",
      "type": "control",
      "actor": "Jiri Prochazka",
      "timestamp": "20:16",
      "successful": false
    },
    {
      "label": "Uchi Mata",
      "type": "takedown",
      "actor": "Jiri Prochazka",
      "timestamp": "20:55"
    },
    {
      "label": "Back Control",
      "type": "control",
      "actor": "Jiri Prochazka",
      "timestamp": "27:35"
    },
    {
      "label": "Back Control",
      "type": "control",
      "actor": "Jiri Prochazka",
      "timestamp": "29:21"
    },
    {
      "label": "Back Control",
      "type": "control",
      "actor": "Jiri Prochazka",
      "timestamp": "29:56"
    },
    {
      "label": "Side Control",
      "type": "control",
      "actor": "Jiri Prochazka",
      "timestamp": "32:10"
    },
    {
      "label": "Back Control",
      "type": "control",
      "actor": "Jiri Prochazka",
      "timestamp": "34:21"
    },
    {
      "label": "Half Guard",
      "type": "guard",
      "actor": "Jiri Prochazka",
      "timestamp": "35:42"
    },
    {
      "label": "Back Control",
      "type": "control",
      "actor": "Jiri Prochazka",
      "timestamp": "35:52"
    },
    {
      "label": "Back Control",
      "type": "control",
      "actor": "Jiri Prochazka",
      "timestamp": "36:27",
      "successful": false
    },
    {
      "label": "Snapdown",
      "type": "takedown",
      "actor": "Jiri Prochazka",
      "timestamp": "36:59"
    },
    {
      "label": "Truck",
      "type": "control",
      "actor": "Jiri Prochazka",
      "timestamp": "37:39"
    },
    {
      "label": "Double Leg Takedown",
      "type": "takedown",
      "actor": "Jiri Prochazka",
      "timestamp": "40:34",
      "successful": false
    },
    {
      "label": "Back Control",
      "type": "control",
      "actor": "Jiri Prochazka",
      "timestamp": "41:31"
    },
    {
      "label": "Back Control",
      "type": "control",
      "actor": "Jiri Prochazka",
      "timestamp": "45:06"
    },
    {
      "label": "Uchi Mata",
      "type": "takedown",
      "actor": "Jiri Prochazka",
      "timestamp": "46:19"
    },
    {
      "label": "Back Control",
      "type": "control",
      "actor": "Jiri Prochazka",
      "timestamp": "46:53"
    },
    {
      "label": "Back Control",
      "type": "control",
      "actor": "Jiri Prochazka",
      "timestamp": "47:36"
    },
    {
      "label": "Stand Up",
      "type": "escape",
      "actor": "Khalil Rountree Jr.: Starts at",
      "timestamp": "48:43"
    },
    {
      "label": "Half Guard",
      "type": "guard",
      "actor": "Jiri Prochazka",
      "timestamp": "51:20"
    },
    {
      "label": "Back Control",
      "type": "control",
      "actor": "Jiri Prochazka",
      "timestamp": "52:31"
    },
    {
      "label": "Half Guard",
      "type": "guard",
      "actor": "Jiri Prochazka",
      "timestamp": "53:11"
    },
    {
      "label": "Single Leg Takedown",
      "type": "takedown",
      "actor": "Jiri Prochazka",
      "timestamp": "53:41"
    },
    {
      "label": "Half Guard",
      "type": "guard",
      "actor": "Jiri Prochazka",
      "timestamp": "53:41"
    },
    {
      "label": "Uchi Mata",
      "type": "takedown",
      "actor": "Jiri Prochazka",
      "timestamp": "54:21"
    }
  ],
  "Carlos Ulberg|Dominick Reyes: Starts at|2025": [
    {
      "label": "Back Control",
      "type": "control",
      "actor": "Carlos Ulberg",
      "timestamp": "0:00"
    },
    {
      "label": "Back Control",
      "type": "control",
      "actor": "Carlos Ulberg",
      "timestamp": "0:44"
    },
    {
      "label": "Float Pass",
      "type": "pass",
      "actor": "Carlos Ulberg",
      "timestamp": "0:56",
      "successful": false
    },
    {
      "label": "Back Control",
      "type": "control",
      "actor": "Carlos Ulberg",
      "timestamp": "2:09"
    },
    {
      "label": "Back Control",
      "type": "control",
      "actor": "Carlos Ulberg",
      "timestamp": "2:44"
    },
    {
      "label": "Back Control",
      "type": "control",
      "actor": "Carlos Ulberg",
      "timestamp": "3:44",
      "successful": false
    },
    {
      "label": "Uchi Mata",
      "type": "takedown",
      "actor": "Carlos Ulberg",
      "timestamp": "4:16"
    }
  ],
  "Paulo Costa|Roman Kopylov: Starts at|2025": [
    {
      "label": "Back Control",
      "type": "control",
      "actor": "Paulo Costa",
      "timestamp": "2:15"
    },
    {
      "label": "Back Control",
      "type": "control",
      "actor": "Paulo Costa",
      "timestamp": "4:00"
    },
    {
      "label": "Back Control",
      "type": "control",
      "actor": "Paulo Costa",
      "timestamp": "4:36"
    },
    {
      "label": "Side Control",
      "type": "control",
      "actor": "Paulo Costa",
      "timestamp": "6:49"
    },
    {
      "label": "Back Control",
      "type": "control",
      "actor": "Paulo Costa",
      "timestamp": "9:00"
    },
    {
      "label": "Half Guard",
      "type": "guard",
      "actor": "Paulo Costa",
      "timestamp": "10:22"
    },
    {
      "label": "Back Control",
      "type": "control",
      "actor": "Paulo Costa",
      "timestamp": "10:31"
    },
    {
      "label": "Back Control",
      "type": "control",
      "actor": "Paulo Costa",
      "timestamp": "11:06",
      "successful": false
    },
    {
      "label": "Snapdown",
      "type": "takedown",
      "actor": "Paulo Costa",
      "timestamp": "11:39"
    },
    {
      "label": "Truck",
      "type": "control",
      "actor": "Paulo Costa",
      "timestamp": "12:19"
    }
  ],
  "Azamat Murzakanov|Aleksandar Rakic: Starts at|2025": [
    {
      "label": "Double Leg Takedown",
      "type": "takedown",
      "actor": "Azamat Murzakanov",
      "timestamp": "0:31"
    },
    {
      "label": "Back Control",
      "type": "control",
      "actor": "Azamat Murzakanov",
      "timestamp": "1:27"
    },
    {
      "label": "Back Control",
      "type": "control",
      "actor": "Azamat Murzakanov",
      "timestamp": "5:05"
    },
    {
      "label": "Back Control",
      "type": "control",
      "actor": "Azamat Murzakanov",
      "timestamp": "6:47"
    },
    {
      "label": "Back Control",
      "type": "control",
      "actor": "Azamat Murzakanov",
      "timestamp": "7:31"
    },
    {
      "label": "Stand Up",
      "type": "escape",
      "actor": "Azamat Murzakanov",
      "timestamp": "8:42"
    }
  ]
}